tuat_feed/__init__.py
tuat_feed/fetch.py
tuat_feed/post.py
tuat_feed-0.2.4.dist-info/WHEEL
tuat_feed-0.2.4.dist-info/METADATA
tuat_feed-0.2.4.dist-info/RECORD
