Metadata-Version: 2.1
Name: tuat-feed
Version: 0.2.4
Summary: Unofficial library for fetching the feed for TUAT
Home-page: https://github.com/pineapplehunter/tuat-feed
License: MIT
Author: Shogo Takata
Author-email: s196643z@st.go.tuat.ac.jp
Requires-Python: >=3.7,<4.0
Classifier: License :: OSI Approved :: MIT License
Classifier: Programming Language :: Python :: 3
Classifier: Programming Language :: Python :: 3.7
Classifier: Programming Language :: Python :: 3.8
Classifier: Programming Language :: Python :: 3.9
Classifier: Programming Language :: Python :: 3.10
Classifier: Programming Language :: Python :: 3.11
Requires-Dist: requests (>=2.26.0,<3.0.0)
Project-URL: Repository, https://github.com/pineapplehunter/tuat-feed
